{"backgroundupdate-enable-unelevated-installations-rollout-3-release":{"slug":"backgroundupdate-enable-unelevated-installations-rollout-3-release","branch":{"slug":"enabled","ratio":1,"feature":{"value":{},"enabled":false,"featureId":"this-is-included-for-desktop-pre-95-support"},"features":[{"value":{"enableUpdatesForUnelevatedInstallations":true},"enabled":true,"featureId":"backgroundUpdate"}]},"active":true,"experimentType":"rollout","source":"rs-loader","userFacingName":"BackgroundUpdate: Enable unelevated installations (Rollout) -- 3-release","userFacingDescription":"Update Firefox when it is not running if the application directory can be written (even without the Mozilla Maintenance Service).","lastSeen":"2024-11-11T18:29:16.165Z","featureIds":["backgroundUpdate"],"prefs":[{"name":"app.update.background.allowUpdatesForUnelevatedInstallations","branch":"user","featureId":"backgroundUpdate","variable":"enableUpdatesForUnelevatedInstallations","originalValue":null}],"isRollout":true},"extensions-migration-in-import-wizard-116-rollout":{"slug":"extensions-migration-in-import-wizard-116-rollout","branch":{"slug":"control","ratio":1,"feature":{"value":{},"enabled":false,"featureId":"this-is-included-for-desktop-pre-95-support"},"features":[{"value":{"useNewWizard":true,"showImportAll":true,"migrateExtensions":true,"showPreferencesEntrypoint":true},"enabled":true,"featureId":"migrationWizard"}]},"active":true,"experimentType":"rollout","source":"rs-loader","userFacingName":"Extensions Migration in Import Wizard - 117+","userFacingDescription":"This rollout makes extension migration available to users migrating from Chrome to Firefox.","lastSeen":"2024-11-11T18:29:16.171Z","featureIds":["migrationWizard"],"prefs":[{"name":"browser.migrate.content-modal.import-all.enabled","branch":"user","featureId":"migrationWizard","variable":"showImportAll","originalValue":null},{"name":"browser.migrate.chrome.extensions.enabled","branch":"user","featureId":"migrationWizard","variable":"migrateExtensions","originalValue":null},{"name":"browser.migrate.preferences-entrypoint.enabled","branch":"user","featureId":"migrationWizard","variable":"showPreferencesEntrypoint","originalValue":null}],"isRollout":true},"upgrade-spotlight-rollout":{"slug":"upgrade-spotlight-rollout","branch":{"slug":"treatment","ratio":1,"feature":{"value":{},"enabled":false,"featureId":"this-is-included-for-desktop-pre-95-support"},"features":[{"value":{"enabled":false},"enabled":true,"featureId":"upgradeDialog"}]},"active":true,"experimentType":"rollout","source":"rs-loader","userFacingName":"Upgrade Spotlight Rollout","userFacingDescription":"Experimenting on onboarding content when you upgrade Firefox.","lastSeen":"2024-11-11T18:29:16.177Z","featureIds":["upgradeDialog"],"prefs":[],"isRollout":true},"launch-firefox-on-os-restart-treatment-a-rollout":{"slug":"launch-firefox-on-os-restart-treatment-a-rollout","branch":{"slug":"treatment-a","ratio":1,"feature":{"value":{},"enabled":false,"featureId":"this-is-included-for-desktop-pre-95-support"},"features":[{"value":{"enabled":true},"enabled":true,"featureId":"windowsLaunchOnLogin"}]},"active":false,"experimentType":"rollout","source":"rs-loader","userFacingName":"Launch Firefox on OS Restart - Treatment A Rollout","userFacingDescription":"Mozilla’s Firefox now offers the option to set up an automatic browser launch at the time of an OS login. This will prove to be useful for those that want to get straight to browsing the web again after previously logging off/out for the day. This will also apply to scenarios where the system requires a mandatory restart due to performance and security updates or various application installations.","lastSeen":"2024-11-11T18:29:16.178Z","featureIds":["windowsLaunchOnLogin"],"prefs":[{"name":"browser.startup.windowsLaunchOnLogin.enabled","branch":"default","featureId":"windowsLaunchOnLogin","variable":"enabled","originalValue":true}],"isRollout":true,"unenrollReason":"recipe-not-seen"},"phc-rollout":{"slug":"phc-rollout","branch":{"slug":"rollout","ratio":1,"feature":{"value":{},"enabled":false,"featureId":"this-is-included-for-desktop-pre-95-support"},"features":[{"value":{"phcEnabled":true},"enabled":true,"featureId":"phc"}]},"active":true,"experimentType":"rollout","source":"rs-loader","userFacingName":"PHC Rollout","userFacingDescription":"Roll out the Probabilistic Heap Checker in Firefox Release.","lastSeen":"2024-11-11T18:29:16.180Z","featureIds":["phc"],"prefs":[{"name":"memory.phc.enabled","branch":"user","featureId":"phc","variable":"phcEnabled","originalValue":null}],"isRollout":true},"highlighting-in-pdfs-rollout":{"slug":"highlighting-in-pdfs-rollout","branch":{"slug":"treatment","ratio":1,"feature":{"value":{},"enabled":false,"featureId":"this-is-included-for-desktop-pre-95-support"},"features":[{"value":{"addHighlight":true},"enabled":true,"featureId":"pdfjs"}]},"active":false,"experimentType":"rollout","source":"rs-loader","userFacingName":"Highlighting in PDFs - Rollout","userFacingDescription":"Feature to highlight text and other content in PDFs","lastSeen":"2024-11-11T18:29:16.182Z","featureIds":["pdfjs"],"prefs":[],"isRollout":true,"unenrollReason":"recipe-not-seen"},"consolidated-search-configuration-row-desktop-relaunch":{"slug":"consolidated-search-configuration-row-desktop-relaunch","branch":{"slug":"rollout","ratio":1,"feature":{"value":{},"enabled":false,"featureId":"this-is-included-for-desktop-pre-95-support"},"features":[{"value":{"newSearchConfigEnabled":true},"enabled":true,"featureId":"search"}]},"active":false,"experimentType":"rollout","source":"rs-loader","userFacingName":"Consolidated Search Configuration (ROW) [Desktop] Relaunch","userFacingDescription":"Consolidated search configuration for desktop and mobile Firefox","lastSeen":"2024-11-11T18:29:16.184Z","featureIds":["search"],"prefs":[{"name":"browser.search.newSearchConfig.enabled","branch":"user","featureId":"search","variable":"newSearchConfigEnabled","originalValue":null}],"isRollout":true,"unenrollReason":"recipe-not-seen"},"long-term-holdback-2024-h2-velocity-desktop":{"slug":"long-term-holdback-2024-h2-velocity-desktop","branch":{"slug":"delivery","ratio":19,"feature":{"value":{},"enabled":false,"featureId":"this-is-included-for-desktop-pre-95-support"},"features":[{"value":{},"enabled":true,"featureId":"no-feature-firefox-desktop"}]},"active":false,"experimentType":"nimbus","source":"rs-loader","userFacingName":"Long term holdback 2024 H2 Velocity Desktop","userFacingDescription":"Long-term holdback for H2 Velocity experiments","lastSeen":"2024-11-11T14:03:34.921Z","featureIds":["no-feature-firefox-desktop"],"prefs":[],"isRollout":false,"unenrollReason":"studies-opt-out"},"disable-redirects-for-authretries":{"slug":"disable-redirects-for-authretries","branch":{"slug":"control","ratio":1,"feature":{"value":{},"enabled":false,"featureId":"this-is-included-for-desktop-pre-95-support"},"features":[{"value":{"redirectForAuthRetriesEnabled":false},"enabled":true,"featureId":"networkingAuth"}]},"active":true,"experimentType":"rollout","source":"rs-loader","userFacingName":"Disable Redirects for Authretries","userFacingDescription":"Rollback Redirection of the http channel for Authentication retries.","lastSeen":"2024-11-11T18:29:16.188Z","featureIds":["networkingAuth"],"prefs":[{"name":"network.auth.use_redirect_for_retries","branch":"default","featureId":"networkingAuth","variable":"redirectForAuthRetriesEnabled","originalValue":false}],"isRollout":true},"encrypted-client-hello-fallback-mechanism":{"slug":"encrypted-client-hello-fallback-mechanism","branch":{"slug":"control","ratio":1,"feature":{"value":{},"enabled":false,"featureId":"this-is-included-for-desktop-pre-95-support"},"features":[{"value":{"insecureFallback":true},"enabled":true,"featureId":"echPrefs"}]},"active":true,"experimentType":"rollout","source":"rs-loader","userFacingName":"Encrypted Client Hello - Fallback Mechanism","userFacingDescription":"This experiment enables a fallback mechanism for Encrypted Client Hello. This feature maximizes compatibility with websites that have misconfigured or unexpected DNS configurations.","lastSeen":"2024-11-11T18:29:16.191Z","featureIds":["echPrefs"],"prefs":[{"name":"network.dns.echconfig.fallback_to_origin_when_all_failed","branch":"default","featureId":"echPrefs","variable":"insecureFallback","originalValue":false}],"isRollout":true},"fx-accounts-ping-release-rollout-2":{"slug":"fx-accounts-ping-release-rollout-2","branch":{"slug":"control","ratio":1,"feature":{"value":{},"enabled":false,"featureId":"this-is-included-for-desktop-pre-95-support"},"features":[{"value":{"pingEnabled":true},"enabled":true,"featureId":"fxaClientAssociation"}]},"active":true,"experimentType":"rollout","source":"rs-loader","userFacingName":"Fx Accounts Ping (release rollout 2)","userFacingDescription":"Enable sending the Fx Accounts ping.","lastSeen":"2024-11-11T18:29:16.193Z","featureIds":["fxaClientAssociation"],"prefs":[{"name":"identity.fxaccounts.telemetry.clientAssociationPing.enabled","branch":"user","featureId":"fxaClientAssociation","variable":"pingEnabled","originalValue":null}],"isRollout":true},"disable-ads-startup-cache":{"slug":"disable-ads-startup-cache","branch":{"slug":"control","ratio":1,"feature":{"value":{},"enabled":false,"featureId":"this-is-included-for-desktop-pre-95-support"},"features":[{"value":{"spocsStartupCache":false},"enabled":true,"featureId":"newtabSpocsCache"}]},"active":true,"experimentType":"rollout","source":"rs-loader","userFacingName":"Disable Ads Startup Cache","userFacingDescription":"Reduce the number of old / out of date ads shown on New Tab","lastSeen":"2024-11-11T18:29:16.196Z","featureIds":["newtabSpocsCache"],"prefs":[{"name":"browser.newtabpage.activity-stream.discoverystream.spocs.startupCache.enabled","branch":"user","featureId":"newtabSpocsCache","variable":"spocsStartupCache","originalValue":null}],"isRollout":true},"disabling-chips-for-v131":{"slug":"disabling-chips-for-v131","branch":{"slug":"control","ratio":1,"feature":{"value":{},"enabled":false,"featureId":"this-is-included-for-desktop-pre-95-support"},"features":[{"value":{"prefs":{"network.cookie.CHIPS.enabled":{"value":false,"branch":"user"}}},"enabled":true,"featureId":"prefFlips"}]},"active":false,"experimentType":"rollout","source":"rs-loader","userFacingName":"Disabling CHIPS for v131","userFacingDescription":"Disabling CHIPS feature for all v131 users due to a google auth login regression","lastSeen":"2024-11-11T18:29:16.205Z","featureIds":["prefFlips"],"prefs":[],"isRollout":true,"prefFlips":{"originalValues":{"network.cookie.CHIPS.enabled":false}},"unenrollReason":"recipe-not-seen"},"fox-doodle-and-tail-fox-2024-rollout":{"slug":"fox-doodle-and-tail-fox-2024-rollout","branch":{"slug":"treatment-a","ratio":1,"feature":{"value":{},"enabled":false,"featureId":"this-is-included-for-desktop-pre-95-support"},"features":[{"value":{"messages":[{"id":"FOX_DOODLE_SET_DEFAULT","groups":["eco"],"content":{"id":"FOX_DOODLE_SET_DEFAULT","screens":[{"id":"FOX_DOODLE_SET_DEFAULT_SCREEN","content":{"logo":{"height":"125px","imageURL":"chrome://activity-stream/content/data/content/assets/fox-doodle-waving.gif","reducedMotionImageURL":"chrome://activity-stream/content/data/content/assets/fox-doodle-waving-static.png"},"title":{"fontSize":"22px","string_id":"fox-doodle-pin-headline","fontWeight":590,"paddingBlock":"4px 0","letterSpacing":0,"paddingInline":"24px"},"subtitle":{"fontSize":"15px","string_id":"fox-doodle-pin-body","lineHeight":"1.4","marginBlock":"8px 16px","letterSpacing":0,"paddingInline":"24px"},"dismiss_button":{"action":{"navigate":true}},"primary_button":{"label":{"string_id":"fox-doodle-pin-primary","marginBlock":"4px 0","paddingBlock":"0","paddingInline":"16px"},"action":{"type":"SET_DEFAULT_BROWSER","navigate":true}},"secondary_button":{"label":{"string_id":"fox-doodle-pin-secondary","marginBlock":"0 -20px"},"action":{"navigate":true}}}}],"backdrop":"transparent","template":"multistage","transitions":true},"trigger":{"id":"defaultBrowserCheck"},"template":"spotlight","frequency":{"lifetime":2},"targeting":"source == 'startup' && !isMajorUpgrade && !activeNotifications && !isDefaultBrowser && !willShowDefaultPrompt && (currentDate|date - profileAgeCreated|date) / 86400000 >= 28 && previousSessionEnd && userPrefs.cfrFeatures == true","_nimbusFeature":"fxms-message-10"},{"id":"TAIL_FOX_SET_DEFAULT","groups":["eco"],"content":{"id":"TAIL_FOX_SET_DEFAULT_CONTENT","screens":[{"id":"TAIL_FOX_SET_DEFAULT_SCREEN","content":{"logo":{"height":"140px","imageURL":"chrome://activity-stream/content/data/content/assets/fox-doodle-tail.png","reducedMotionImageURL":"chrome://activity-stream/content/data/content/assets/fox-doodle-tail.png"},"title":{"fontSize":"22px","string_id":"tail-fox-spotlight-title","fontWeight":590,"paddingBlock":"4px 0","letterSpacing":0,"paddingInline":"24px"},"subtitle":{"fontSize":"15px","string_id":"tail-fox-spotlight-subtitle","lineHeight":"1.4","marginBlock":"8px 16px","letterSpacing":0,"paddingInline":"24px"},"dismiss_button":{"action":{"navigate":true}},"primary_button":{"label":{"string_id":"tail-fox-spotlight-primary-button","marginBlock":"4px 0","paddingBlock":"0","paddingInline":"16px"},"action":{"type":"SET_DEFAULT_BROWSER","navigate":true}},"secondary_button":{"label":{"string_id":"tail-fox-spotlight-secondary-button","marginBlock":"0 -20px"},"action":{"navigate":true}}}}],"backdrop":"transparent","template":"multistage","transitions":true},"trigger":{"id":"defaultBrowserCheck"},"template":"spotlight","frequency":{"lifetime":1},"targeting":"source == 'startup' && !isMajorUpgrade && !activeNotifications && !isDefaultBrowser && !willShowDefaultPrompt && (currentDate|date - profileAgeCreated|date) / 86400000 < 28 && (currentDate|date - profileAgeCreated|date) / 86400000 >= 7 && previousSessionEnd && userPrefs.cfrFeatures == true","_nimbusFeature":"fxms-message-10"}],"template":"multi"},"enabled":true,"featureId":"fxms-message-10"}],"firefoxLabsTitle":null},"active":false,"experimentType":"rollout","source":"rs-loader","userFacingName":"Fox Doodle and Tail Fox 2024 - Rollout","userFacingDescription":"Set to default prompt highlighting benefits of choosing Firefox","lastSeen":"2024-11-22T11:35:20.164Z","featureIds":["fxms-message-10"],"prefs":[],"isRollout":true,"unenrollReason":"recipe-not-seen"},"new-alt-text-flow-and-generation-treatment-a-rollout-for-non-en-locales":{"slug":"new-alt-text-flow-and-generation-treatment-a-rollout-for-non-en-locales","branch":{"slug":"treatment-a","ratio":1,"feature":{"value":{},"enabled":false,"featureId":"this-is-included-for-desktop-pre-95-support"},"features":[{"value":{"enableAltText":false,"browserMlEnable":false,"enableUpdatedAddImage":true},"enabled":true,"featureId":"pdfjs"}],"firefoxLabsTitle":null},"active":true,"experimentType":"rollout","source":"rs-loader","userFacingName":"New alt text flow in PDFs - for non-EN locales","userFacingDescription":"This experiment offers users improved alt text flow upon adding an image to a PDF and/or functionality that generates alt text for images they add to PDFs using a small, local, and fully private language model.","lastSeen":"2024-12-17T15:09:10.516Z","featureIds":["pdfjs"],"prefs":[{"name":"pdfjs.enableAltText","branch":"default","featureId":"pdfjs","variable":"enableAltText","originalValue":false},{"name":"browser.ml.enable","branch":"default","featureId":"pdfjs","variable":"browserMlEnable","originalValue":false},{"name":"pdfjs.enableUpdatedAddImage","branch":"default","featureId":"pdfjs","variable":"enableUpdatedAddImage","originalValue":false}],"isRollout":true},"long-term-holdback-2025h1-growth-desktop":{"slug":"long-term-holdback-2025h1-growth-desktop","branch":{"slug":"delivery","ratio":19,"feature":{"value":{},"enabled":false,"featureId":"this-is-included-for-desktop-pre-95-support"},"features":[{"value":{},"enabled":true,"featureId":"no-feature-firefox-desktop"}],"firefoxLabsTitle":null},"active":true,"experimentType":"nimbus","source":"rs-loader","userFacingName":"Long term holdback 2025H1 Growth Desktop","userFacingDescription":"Long-term holdback for 2025 H1 Growth experiments","lastSeen":"2025-01-10T06:30:39.702Z","featureIds":["no-feature-firefox-desktop"],"prefs":[],"isRollout":false},"fox-doodle-and-tail-fox-2025-v2-rollout":{"slug":"fox-doodle-and-tail-fox-2025-v2-rollout","branch":{"slug":"treatment-a","ratio":1,"feature":{"value":{},"enabled":false,"featureId":"this-is-included-for-desktop-pre-95-support"},"features":[{"value":{"messages":[{"id":"FOX_DOODLE_SET_DEFAULT","groups":["eco"],"content":{"id":"FOX_DOODLE_SET_DEFAULT","screens":[{"id":"FOX_DOODLE_SET_DEFAULT_SCREEN","content":{"logo":{"height":"125px","imageURL":"chrome://activity-stream/content/data/content/assets/fox-doodle-waving.gif","reducedMotionImageURL":"chrome://activity-stream/content/data/content/assets/fox-doodle-waving-static.png"},"title":{"fontSize":"22px","string_id":"fox-doodle-pin-headline","fontWeight":590,"paddingBlock":"4px 0","letterSpacing":0,"paddingInline":"24px"},"subtitle":{"fontSize":"15px","string_id":"fox-doodle-pin-body","lineHeight":"1.4","marginBlock":"8px 16px","letterSpacing":0,"paddingInline":"24px"},"dismiss_button":{"action":{"navigate":true}},"primary_button":{"label":{"string_id":"fox-doodle-pin-primary","marginBlock":"4px 0","paddingBlock":"0","paddingInline":"16px"},"action":{"type":"SET_DEFAULT_BROWSER","navigate":true}},"secondary_button":{"label":{"string_id":"fox-doodle-pin-secondary","marginBlock":"0 -20px"},"action":{"navigate":true}}}}],"backdrop":"transparent","template":"multistage","transitions":true},"trigger":{"id":"defaultBrowserCheck"},"template":"spotlight","frequency":{"lifetime":2},"targeting":"source == 'startup' && !isMajorUpgrade && !activeNotifications && !isDefaultBrowser && !willShowDefaultPrompt && (currentDate|date - profileAgeCreated|date) / 86400000 >= 28 && previousSessionEnd && userPrefs.cfrFeatures == true","_nimbusFeature":"fxms-message-10"},{"id":"TAIL_FOX_SET_DEFAULT","groups":["eco"],"content":{"id":"TAIL_FOX_SET_DEFAULT_CONTENT","screens":[{"id":"TAIL_FOX_SET_DEFAULT_SCREEN","content":{"logo":{"height":"140px","imageURL":"chrome://activity-stream/content/data/content/assets/fox-doodle-tail.png","reducedMotionImageURL":"chrome://activity-stream/content/data/content/assets/fox-doodle-tail.png"},"title":{"fontSize":"22px","string_id":"tail-fox-spotlight-title","fontWeight":590,"paddingBlock":"4px 0","letterSpacing":0,"paddingInline":"24px"},"subtitle":{"fontSize":"15px","string_id":"tail-fox-spotlight-subtitle","lineHeight":"1.4","marginBlock":"8px 16px","letterSpacing":0,"paddingInline":"24px"},"dismiss_button":{"action":{"navigate":true}},"primary_button":{"label":{"string_id":"tail-fox-spotlight-primary-button","marginBlock":"4px 0","paddingBlock":"0","paddingInline":"16px"},"action":{"type":"SET_DEFAULT_BROWSER","navigate":true}},"secondary_button":{"label":{"string_id":"tail-fox-spotlight-secondary-button","marginBlock":"0 -20px"},"action":{"navigate":true}}}}],"backdrop":"transparent","template":"multistage","transitions":true},"trigger":{"id":"defaultBrowserCheck"},"template":"spotlight","frequency":{"lifetime":1},"targeting":"source == 'startup' && !isMajorUpgrade && !activeNotifications && !isDefaultBrowser && !willShowDefaultPrompt && (currentDate|date - profileAgeCreated|date) / 86400000 < 28 && (currentDate|date - profileAgeCreated|date) / 86400000 >= 7 && previousSessionEnd && userPrefs.cfrFeatures == true","_nimbusFeature":"fxms-message-10"}],"template":"multi"},"enabled":true,"featureId":"fxms-message-10"}],"firefoxLabsTitle":null},"active":true,"experimentType":"rollout","source":"rs-loader","userFacingName":"Fox Doodle and Tail Fox 2025 V2 - Rollout","userFacingDescription":"Set to default prompt highlighting benefits of choosing Firefox","lastSeen":"2025-01-10T06:35:36.584Z","featureIds":["fxms-message-10"],"prefs":[],"isRollout":true},"user_restricted-for-content-process-rollout-134":{"slug":"user_restricted-for-content-process-rollout-134","branch":{"slug":"userrestricted","ratio":1,"feature":{"value":{},"enabled":false,"featureId":"this-is-included-for-desktop-pre-95-support"},"features":[{"value":{"Level":8},"enabled":true,"featureId":"contentProcessSandbox"}],"firefoxLabsTitle":null},"active":true,"experimentType":"rollout","source":"rs-loader","userFacingName":"USER_RESTRICTED for content process - Rollout 134","userFacingDescription":"Rollout of process sandbox improvement for content processes.","lastSeen":"2025-01-28T12:09:41.347Z","featureIds":["contentProcessSandbox"],"prefs":[{"name":"security.sandbox.content.level","branch":"user","featureId":"contentProcessSandbox","variable":"Level","originalValue":null}],"isFirefoxLabsOptIn":false,"firefoxLabsTitle":null,"firefoxLabsDescription":null,"isRollout":true}}